{
    "$schema": "http://json.schemastore.org/template",
    "author": "Me",
    "classifications": [ "Common", "Console", "WebApi" ],
    "identity": "ExampleTemplate.AsyncProject",
    "name": "Example templates: async project",
    "shortName": "microsservico",
    "tags": {
      "language": "C#",
      "type": "project"
    },
    "sourceName": "Pedidos",
    "preferNameDirectory":true,
    "symbolInfo": {
      "audience": {
        "longName": "audience",
        "shortName": "au"
      }
    },
    "symbols": {
      "audience": {
        "type": "parameter",
        "datatype": "string",
        "description": "Your Auth0 client id.",
        "defaultValue": "WebApi",
        "replaces":"AUDIENCE-PATH"
      }   
    }
  }